{
  "start_time": "2025-09-01T21:58:05.996221709+08:00",
  "end_time": "2025-09-01T21:58:48.914274+08:00",
  "duration": 42918052291,
  "source_directory": "/var/folders/13/mnd_v68d3h3c__ws8xh9jcr40000gp/T/TestUserInteractionScenario2350035653/001",
  "total_files": 2,
  "processed_files": 2,
  "successful_files": 0,
  "failed_files": 0,
  "skipped_files": 2,
  "total_size_before": 33,
  "total_size_after": 33,
  "space_saved": 0,
  "compression_ratio": 0,
  "conversion_mode": "auto+",
  "file_details": [
    {
      "original_path": "/var/folders/13/mnd_v68d3h3c__ws8xh9jcr40000gp/T/TestUserInteractionScenario2350035653/001/test_png.png",
      "output_path": "/var/folders/13/mnd_v68d3h3c__ws8xh9jcr40000gp/T/TestUserInteractionScenario2350035653/001/test_png.png",
      "original_size": 16,
      "output_size": 16,
      "compression_ratio": 0,
      "original_format": ".png",
      "output_format": ".png",
      "processing_time": 36890698167,
      "method": "image_conversion",
      "success": true,
      "media_info": {
        "full_path": "/var/folders/13/mnd_v68d3h3c__ws8xh9jcr40000gp/T/TestUserInteractionScenario2350035653/001/test_png.png",
        "file_size": 16,
        "mod_time": "2025-09-01T21:58:05.885430163+08:00",
        "codec": "png",
        "duration": 0.04,
        "bitrate": 3200,
        "frame_rate": 25
      }
    },
    {
      "original_path": "/var/folders/13/mnd_v68d3h3c__ws8xh9jcr40000gp/T/TestUserInteractionScenario2350035653/001/test_image.jpg",
      "output_path": "/var/folders/13/mnd_v68d3h3c__ws8xh9jcr40000gp/T/TestUserInteractionScenario2350035653/001/test_image.jpg",
      "original_size": 17,
      "output_size": 17,
      "compression_ratio": 0,
      "original_format": ".jpg",
      "output_format": ".jpg",
      "processing_time": 42917986459,
      "method": "image_conversion",
      "success": true,
      "media_info": {
        "full_path": "/var/folders/13/mnd_v68d3h3c__ws8xh9jcr40000gp/T/TestUserInteractionScenario2350035653/001/test_image.jpg",
        "file_size": 17,
        "mod_time": "2025-09-01T21:58:05.881102319+08:00",
        "codec": "mjpeg",
        "duration": 0.04,
        "bitrate": 3400,
        "frame_rate": 25,
        "color_space": "bt470bg"
      }
    }
  ],
  "format_summary": {
    ".jpg": {
      "count": 1,
      "total_size_before": 17,
      "total_size_after": 17,
      "average_compression": 0
    },
    ".png": {
      "count": 1,
      "total_size_before": 16,
      "total_size_after": 16,
      "average_compression": 0
    }
  },
  "system_info": {
    "os": "darwin",
    "arch": "arm64",
    "cpu_cores": 4,
    "concurrency": 4,
    "memory_used_mb": 0
  },
  "errors": null
}